{
  "METADATA_VERSION": 20002,
  "allow_disabled_algorithms": false,
  "app-release-signed.apk": {
    "hash": "c941a22fff98c71e6b264adb1e5d0a7c78834bbc3acbf4d20684f5cf946cafdb",
    "hashType": "sha256",
    "uses-permission": [
      [
        "android.permission.POST_NOTIFICATIONS",
        null
      ],
      [
        "io.tapxcard.app.twa.DYNAMIC_RECEIVER_NOT_EXPORTED_PERMISSION",
        null
      ]
    ],
    "uses-permission-sdk-23": [],
    "features": [],
    "icons_src": {},
    "icons": {},
    "antiFeatures": {},
    "packageName": "io.tapxcard.app.twa",
    "versionCode": 1,
    "name": "TapXCard",
    "versionName": "1",
    "minSdkVersion": 21,
    "targetSdkVersion": 35,
    "sig": "4e87b885979917ecea2da0a86cd3af86",
    "signer": "54b839105dc302c4c6fcd3b10f6ad42273c41c2d3b3e3064ccf0881940e55c11",
    "size": 1396853,
    "apkName": "app-release-signed.apk",
    "added": 1754918714.0
  },
  ".DS_Store": {
    "name": ".DS_Store",
    "apkName": ".DS_Store",
    "hash": "20a346e57688ed73a20197eb4560d5efc940945990d701eb6008602e47fb6190",
    "hashType": "sha256",
    "ipfsCIDv1": null,
    "versionCode": 0,
    "versionName": "20a346e",
    "packageName": "20a346e57688ed73a20197eb4560d5efc940945990d701eb6008602e47fb6190",
    "size": 8196,
    "added": 1754920188.841327
  }
}